README.md
setup.py
yield_from.egg-info/PKG-INFO
yield_from.egg-info/SOURCES.txt
yield_from.egg-info/dependency_links.txt
yield_from.egg-info/requires.txt
yield_from.egg-info/top_level.txt
yieldfrom/__init__.py