Metadata-Version: 1.1
Name: yield-from
Version: 0.0.1
Summary: A backport of Python 3's "yield from" to Python 2.7.
Home-page: https://github.com/hchasestevens/yield-from
Author: H. Chase Stevens
Author-email: chase@chasestevens.com
License: MIT
Keywords: backport compatibility generators
Platform: UNKNOWN
Classifier: Development Status :: 3 - Alpha
Classifier: Programming Language :: Python
Classifier: Programming Language :: Python :: 2
Classifier: Programming Language :: Python :: 2.7
Classifier: Intended Audience :: Developers
Classifier: Operating System :: OS Independent
Classifier: License :: OSI Approved :: MIT License
Classifier: Natural Language :: English
